xy_request_handler__feedback/Feedbacks.py
xy_request_handler__feedback/__init__.py
xy_request_handler__feedback/urls.py
xy_request_handler__feedback/__pycache__/Feedbacks.cpython-311.pyc
xy_request_handler__feedback/__pycache__/__init__.cpython-311.pyc
xy_request_handler_feedback-1.0.0.dist-info/LICENSE
xy_request_handler_feedback-1.0.0.dist-info/METADATA
xy_request_handler_feedback-1.0.0.dist-info/WHEEL
xy_request_handler_feedback-1.0.0.dist-info/top_level.txt
xy_request_handler_feedback-1.0.0.dist-info/RECORD
