Metadata-Version: 2.1
Name: xy_request_handler__feedback
Version: 1.0.0
Summary: 反馈业务请求模块
Author-email: 余洋 <yuyangit.0515@qq.com>
Classifier: Programming Language :: Python :: 3
Requires-Python: >=3.11.3
License-File: LICENSE
Requires-Dist: xy-type
Requires-Dist: xy-string
Requires-Dist: xy-django-app-feedback
Requires-Dist: xy-django-app-resource
Requires-Dist: xy-request-handler-api
